kinematic_constraint/__init__.py
kinematic_constraint/dof.py
kinematic_constraint/geometry.py
kinematic_constraint/linalg.py
kinematic_constraint/visualize.py
kinematic_constraint-0.1.1.dist-info/LICENSE.md
kinematic_constraint-0.1.1.dist-info/METADATA
kinematic_constraint-0.1.1.dist-info/WHEEL
kinematic_constraint-0.1.1.dist-info/RECORD
