Metadata-Version: 2.1
Name: kinematic-constraint
Version: 0.1.1
Summary: Solver for rigid body degrees of freedom with the theory of kinematic constraint (aka exact constraint).
Home-page: https://github.com/mvernacc/kinematic_constraint
Author: Matthew Vernacchia
Author-email: mvernacc@mit.edu
Requires-Python: >=3.11,<4.0
Classifier: Programming Language :: Python :: 3
Classifier: Programming Language :: Python :: 3.11
Classifier: Programming Language :: Python :: 3.12
Requires-Dist: matplotlib (>=3.9.0,<4.0.0)
Requires-Dist: scipy (>=1.13.1,<2.0.0)
Project-URL: Repository, https://github.com/mvernacc/kinematic_constraint
